willtools/__init__.py
willtools/fs.py
willtools/id.py
willtools/image.py
willtools/st.py
willtools-0.1.12.dist-info/METADATA
willtools-0.1.12.dist-info/WHEEL
willtools-0.1.12.dist-info/top_level.txt
willtools-0.1.12.dist-info/RECORD
